freebooks/__init__.py
freebooks/logger.py
freebooks/main.py
freebooks/aax_tables/Makefile
freebooks/aax_tables/README.md
freebooks/aax_tables/__init__.py
freebooks/aax_tables/alglib0.so
freebooks/aax_tables/alglib1.cpp
freebooks/aax_tables/alglib1.so
freebooks/aax_tables/audible_byte#4-4_0_10000x789935_0.rtc
freebooks/aax_tables/audible_byte#4-4_1_10000x791425_0.rtc
freebooks/aax_tables/audible_byte#4-4_2_10000x790991_0.rtc
freebooks/aax_tables/audible_byte#4-4_3_10000x792120_0.rtc
freebooks/aax_tables/audible_byte#4-4_4_10000x790743_0.rtc
freebooks/aax_tables/audible_byte#4-4_5_10000x790568_0.rtc
freebooks/aax_tables/audible_byte#4-4_6_10000x791458_0.rtc
freebooks/aax_tables/audible_byte#4-4_7_10000x791707_0.rtc
freebooks/aax_tables/audible_byte#4-4_8_10000x790202_0.rtc
freebooks/aax_tables/audible_byte#4-4_9_10000x791022_0.rtc
freebooks/aax_tables/bswap.h
freebooks/aax_tables/charset.txt
freebooks/aax_tables/demo.sh
freebooks/aax_tables/generate-tables.sh
freebooks/aax_tables/rcrack
freebooks/aax_tables/sha1.c
freebooks/aax_tables/sha1.h
freebooks/aax_tables/run/alglib1.dll
freebooks/aax_tables/run/alglib1.dll.md5
freebooks/aax_tables/run/charset.txt
freebooks/aax_tables/run/rcrack.exe
freebooks/aax_tables/run/rcrack.exe.md5
freebooks/aax_tables/run/readme.txt
freebooks-0.1.4.dist-info/licenses/LICENSE
freebooks-0.1.4.dist-info/METADATA
freebooks-0.1.4.dist-info/WHEEL
freebooks-0.1.4.dist-info/entry_points.txt
freebooks-0.1.4.dist-info/top_level.txt
freebooks-0.1.4.dist-info/RECORD
