Metadata-Version: 2.4
Name: freebooks
Version: 0.1.4
Summary: Convert Audible AAX to common audio formats (requires ffmpeg, awk, grep installed in /usr/bin).
Home-page: https://github.com/leshawn-rice/freebooks
Author: Leshawn Rice
Author-email: leshawn.rice@yahoo.com
License: PolyForm Noncommercial License 1.0.0
Classifier: Programming Language :: Python :: 3
Classifier: License :: Other/Proprietary License
Classifier: Operating System :: POSIX :: Linux
Requires-Python: >=3.7
License-File: LICENSE
Dynamic: author
Dynamic: author-email
Dynamic: classifier
Dynamic: description
Dynamic: description-content-type
Dynamic: home-page
Dynamic: license
Dynamic: license-file
Dynamic: requires-python
Dynamic: summary
